docs/faq.md
docs/filesystem-server-usage.md
docs/index.md
docs/stdio-tool-execution.md
docs/tool-discovery.md
docs/api/cli.md
docs/api/schema.md
docs/cli/cleanup.md
docs/cli/config.md
docs/cli/connect.md
docs/cli/create.md
docs/cli/deploy.md
docs/cli/discover-tools.md
docs/cli/index.md
docs/cli/interactive-cli.doc
docs/cli/interactive.md
docs/cli/list.md
docs/cli/logs.md
docs/cli/run-tool.md
docs/cli/run.md
docs/cli/shell.md
docs/cli/stop.md
docs/cli/tools.md
docs/client/examples.md
docs/client/index.md
docs/client/servers.md
docs/client/templates.md
docs/client/tools.md
docs/development/architecture.md
docs/development/setup.md
docs/getting-started/configuration.md
docs/getting-started/first-deployment.md
docs/getting-started/installation.md
docs/getting-started/quickstart.md
docs/guides/contributing.md
docs/guides/creating-templates.md
docs/guides/deployment.md
docs/guides/testing.md
docs/guides/troubleshooting.md
docs/guides/usage.md
docs/interactive-cli/call.md
docs/interactive-cli/clear_config.md
docs/interactive-cli/commands.md
docs/interactive-cli/config.md
docs/interactive-cli/help.md
docs/interactive-cli/list_servers.md
docs/interactive-cli/quit.md
docs/interactive-cli/show_config.md
docs/interactive-cli/templates.md
docs/interactive-cli/tools.md
docs/server-templates/available.md
docs/server-templates/index.md
docs/server-templates/demo/index.md
docs/server-templates/demo/usage.md
docs/server-templates/file-server/index.md
docs/server-templates/file-server/usage.md
docs/stylesheets/extra.css
docs/templates/creating.md
docs/templates/development.md
docs/templates/file-server.md
docs/templates/index.md
docs/templates/template-json-reference.md
docs/templates/testing.md
docs/user-guide/cli-reference.md
docs/user-guide/client-usage.md
docs/user-guide/monitoring.md
examples/config/file-server-config.json
examples/config/nested-config-test.json
examples/docker-compose/development.yml
examples/docker-compose/production.yml
examples/kubernetes/file-server.yaml
mcp_templates-1.0.12.dist-info/licenses/LICENSE
mcp_templates-1.0.12.dist-info/licenses/NOTICE
mcp_templates-1.0.12.dist-info/METADATA
mcp_templates-1.0.12.dist-info/WHEEL
mcp_templates-1.0.12.dist-info/entry_points.txt
mcp_templates-1.0.12.dist-info/top_level.txt
mcp_templates-1.0.12.dist-info/RECORD
