Metadata-Version: 2.4
Name: mcp-templates
Version: 1.0.12
Summary: MCP-Server-Templates: Easy, zero-config deployment for Model Context Protocol servers
Author-email: Sam Arora <tooling@dataeverything.com>
License-Expression: Elastic-2.0
Project-URL: Bug-Reports, https://github.com/Data-Everything/mcp-server-templates/issues
Project-URL: Source, https://github.com/Data-Everything/mcp-server-templates
Project-URL: Documentation, https://data-everything.github.io/mcp-server-templates
Project-URL: Issue-Tracker, https://github.com/Data-Everything/mcp-server-templates/issues
Keywords: MCP,Model Context Protocol,AI Tools,Server Templates,Docker,Kubernetes
Classifier: Development Status :: 4 - Beta
Classifier: Intended Audience :: Developers
Classifier: Operating System :: OS Independent
Classifier: Programming Language :: Python :: 3
Classifier: Programming Language :: Python :: 3.10
Classifier: Programming Language :: Python :: 3.11
Classifier: Programming Language :: Python :: 3.12
Classifier: Programming Language :: Python :: 3.13
Classifier: Topic :: Software Development :: Libraries :: Python Modules
Classifier: Topic :: System :: Systems Administration
Requires-Python: >=3.10
License-File: LICENSE
License-File: NOTICE
Requires-Dist: rich>=13.0.0
Requires-Dist: pyyaml>=6.0
Requires-Dist: requests>=2.25.1
Requires-Dist: cmd2==2.7
Requires-Dist: aiohttp>=3.8.0
Requires-Dist: setuptools_scm>=8.3.1
Requires-Dist: typer>=0.16.0
Dynamic: license-file
